cryptopr/__init__.py
cryptopr/main.py
cryptopr-0.1.0.dist-info/METADATA
cryptopr-0.1.0.dist-info/WHEEL
cryptopr-0.1.0.dist-info/top_level.txt
cryptopr-0.1.0.dist-info/RECORD
