Metadata-Version: 2.4
Name: cryptopr
Version: 0.1.0
Requires-Python: >=3.9
Requires-Dist: setuptools>=80.9.0
